AUTHORS.txt
LICENSE.txt
MANIFEST.in
README.rst
setup.py
finch/__init__.py
finch/admin.py
finch/forms.py
finch/managers.py
finch/middleware.py
finch/models.py
finch/project_settings.py
finch/reveplugins.py
finch/search_sites.py
finch/settings.py
finch/signals.py
finch/urls.py
finch/views.py
finch/management/__init__.py
finch/management/commands/__init__.py
finch/management/commands/make_homepage.py
finch/static/finch/css/finch.css
finch/static/finch/js/jquery.finch.js
finch/static/finch/js/jquery/plugins/jquery-treeview/changelog.txt
finch/static/finch/js/jquery/plugins/jquery-treeview/jquery.treeview.async.js
finch/static/finch/js/jquery/plugins/jquery-treeview/jquery.treeview.css
finch/static/finch/js/jquery/plugins/jquery-treeview/jquery.treeview.js
finch/static/finch/js/jquery/plugins/jquery-treeview/jquery.treeview.min.js
finch/static/finch/js/jquery/plugins/jquery-treeview/jquery.treeview.pack.js
finch/static/finch/js/jquery/plugins/jquery-treeview/images/file.gif
finch/static/finch/js/jquery/plugins/jquery-treeview/images/folder-closed.gif
finch/static/finch/js/jquery/plugins/jquery-treeview/images/folder.gif
finch/static/finch/js/jquery/plugins/jquery-treeview/images/minus.gif
finch/static/finch/js/jquery/plugins/jquery-treeview/images/plus.gif
finch/static/finch/js/jquery/plugins/jquery-treeview/images/treeview-black-line.gif
finch/static/finch/js/jquery/plugins/jquery-treeview/images/treeview-black.gif
finch/static/finch/js/jquery/plugins/jquery-treeview/images/treeview-default-line.gif
finch/static/finch/js/jquery/plugins/jquery-treeview/images/treeview-default.gif
finch/static/finch/js/jquery/plugins/jquery-treeview/images/treeview-famfamfam-line.gif
finch/static/finch/js/jquery/plugins/jquery-treeview/images/treeview-famfamfam.gif
finch/static/finch/js/jquery/plugins/jquery-treeview/images/treeview-gray-line.gif
finch/static/finch/js/jquery/plugins/jquery-treeview/images/treeview-gray.gif
finch_cms.egg-info/PKG-INFO
finch_cms.egg-info/SOURCES.txt
finch_cms.egg-info/dependency_links.txt
finch_cms.egg-info/not-zip-safe
finch_cms.egg-info/requires.txt
finch_cms.egg-info/top_level.txt