Metadata-Version: 1.1
Name: finch-cms
Version: 0.8.7
Summary: Simple but flexible CMS for django
Home-page: https://github.com/pterk/finch-cms
Author: Peter van Kampen
Author-email: pterk@datatailors.com
License: BSD
Keywords: django cms
Platform: UNKNOWN
Classifier: Development Status :: 4 - Beta
Classifier: Environment :: Web Environment
Classifier: Intended Audience :: Developers
Classifier: Operating System :: OS Independent
Classifier: License :: OSI Approved :: BSD License
Classifier: Programming Language :: Python
Classifier: Framework :: Django
